Metadata-Version: 2.1
Name: megicparc
Version: 1.0.1
Summary: MEG Informed Cortical Parcellations
Author: Sara Sommariva
Author-email: sommariva@dima.unige.it
Classifier: License :: OSI Approved :: MIT License
Classifier: Programming Language :: Python
Classifier: Programming Language :: Python :: 3.6
Classifier: Programming Language :: Python :: Implementation :: CPython
